statisk/ImageFilter.py
statisk/Log.py
statisk/PyStatisk.py
statisk/__init__.py
statisk/test_Log.py
Statisk-1.2.0.dist-info/LICENSE
Statisk-1.2.0.dist-info/METADATA
Statisk-1.2.0.dist-info/WHEEL
Statisk-1.2.0.dist-info/entry_points.txt
Statisk-1.2.0.dist-info/top_level.txt
Statisk-1.2.0.dist-info/RECORD
