Metadata-Version: 2.1
Name: Statisk
Version: 1.2.0
Summary: Simple markdown based low bandwidth static site generator
Home-page: https://github.com/fiskurgit/PyStatisk
Author: fiskurgit
Author-email: fiskdebug@gmail.com
License: GNU General Public License v3.0
Platform: UNKNOWN
Requires-Python: >=3
Requires-Dist: Pillow
Requires-Dist: markdown
Requires-Dist: termcolor
